yandexid/__init__.py
yandexid/__meta.py
yandexid/avatar_utils.py
yandexid/errors/__init__.py
yandexid/errors/yandexoauth.py
yandexid/schemas/__init__.py
yandexid/schemas/yandexid.py
yandexid/schemas/yandexoauth.py
yandexid/validators.py
yandexid/yandexid/__init__.py
yandexid/yandexid/async_yandexid.py
yandexid/yandexid/yandexid.py
yandexid/yandexoauth/__init__.py
yandexid/yandexoauth/async_yandexoauth.py
yandexid/yandexoauth/yandexoauth.py
yandexid-0.3.1.dist-info/METADATA
yandexid-0.3.1.dist-info/WHEEL
yandexid-0.3.1.dist-info/LICENSE
yandexid-0.3.1.dist-info/RECORD
